{"resource":{"classification":{"type":"Dataset"},"collection":["Robert Koch Institute"],"descriptions":[{"language":"DE (German)","text":"Das Vorhaben „Abwassermonitoring für die epidemiologische Lagebewertung“ (AMELAG) läuft vom 22.11.2022 bis zum 31.12.2024. Behörden, Kläranlagen und Labore arbeiten zusammen, um Proben zu nehmen, zu analysieren und zu bewerten. Das Ziel dieses Vorhabens ist es, SARS-CoV-2-Nachweise aus dem Abwasser als zusätzlichen Indikator zur epidemiologischen Lagebewertung auf Länder- und Bundesebene zu etablieren. Ebenso ist es das Ziel, Strukturen und Prozesse für ein bundesweites Netzwerk für die Abwassersurveillance weiter auszubauen, Konzepte für eine Verstetigung zu erstellen und die Möglichkeiten für ein Monitoring von weiteren Krankheitserregern im Abwasser zu erforschen.\nAbwassersurveillance ist eine Technik, um Erreger im Abwasser nachzuweisen, um Gesundheitsschutzmaßnahmen besser steuern zu können. Abwasserdaten erlauben keine genaue Einschätzung von Krankheitsschwere oder der Belastung des Gesundheitssystems. Bei der epidemiologischen Bewertung sollten die Daten mit anderen Indikatoren, z.B. aus der syndromischen Surveillance, kombiniert werden."}],"titles":[{"language":"DE (German)","text":"Abwassersurveillance AMELAG"}],"ids":[{"identifier":"10.5281/zenodo.13982570","typeGeneral":"Dataset","relationType":"A references B","scheme":"DOI"},{"identifier":"https://github.com/robert-koch-institut/Abwassersurveillance_AMELAG","relationType":"A references B","typeGeneral":"Dataset","scheme":"URL"}],"provenance":{"dataSource":"Automatically uploaded: Other"},"keywords":[{"label":"COVID-19","code":"D000086382"},{"label":"SARS-CoV-2","code":"D000086402"},{"label":"Abwasserbasierte epidemiologische Überwachung","code":"D000079686"},{"label":"Wastewater-Based Epidemiological Monitoring","code":"D000079686"},{"label":"Epidemiologie","code":"info:ddc/22/de//614.4"},{"label":"Gesundheitsberichterstattung","code":"info:ddc/22/de//614.42"},{"label":"Public health surveillance","code":"info:ddc/22/eng//614.42"},{"label":"Epidemiology","code":"info:ddc/22/eng//614.4"},{"label":"Deutschland"},{"label":"Germany"},{"label":"Open Data"},{"label":"Offene Daten"},{"label":"RKI"}],"languages":["DE (German)"],"nonStudyDetails":{"useRights":{"confirmations":{"authority":true,"irrevocability":true,"terms":true,"supportByLicensing":true},"label":"CC BY 4.0 (Creative Commons Attribution 4.0 International)"},"version":"2024-10-22"},"webpage":"https://robert-koch-institut.github.io/Abwassersurveillance_AMELAG","contributors":[{"affiliations":[{"name":"Robert Koch-Institut"}],"nameType":"Personal","personal":{"type":"Creator/Author","givenName":"Fachgebiet 32","familyName":"Robert Koch-Institut"}}],"identifier":"3059"}}