{
  "fields": [
    {
      "name": "standort",
      "type": "string",
      "description": "Standort, an dem sich die Kläranlage befindet."
    },
    {
      "name": "bundesland",
      "type": "string",
      "description": "Bundesland (abgekürzt), in dem sich die Kläranlage befindet.",
      "constraints": {
        "enum": [
          [
            "BB",
            "BE",
            "BW",
            "BY",
            "HB",
            "HE",
            "HH",
            "MV",
            "NI",
            "NW",
            "RP",
            "SH",
            "SL",
            "SN",
            "ST",
            "TH"
          ]
        ]
      }
    },
    {
      "name": "datum",
      "type": "date",
      "description": "Datum, an dem die 24-Stunden-Mischprobe in der Kläranlage begonnen hat.",
      "missingValues": [
        "NA"
      ]
    },
    {
      "name": "viruslast",
      "type": "number",
      "description": "Gemessene SARS-CoV-2-Viruslast in Genkopien pro Liter.",
      "missingValues": [
        "NA"
      ],
      "constraints": {
        "minimum": 0
      }
    },
    {
      "name": "loess_vorhersage",
      "type": "number",
      "description": "Die mittels einer LOESS-Regression (optimiert mittels GCV-Kriterium für die 10er-logarithmierten Viruslasten) vorhergesagten Viruslasten.",
      "missingValues": [
        "NA"
      ],
      "constraints": {
        "minimum": 0
      }
    },
    {
      "name": "loess_obere_schranke",
      "type": "number",
      "description": "Obere Grenze des punktweisen 95%-Konfidenzintervalls des LOESS-Vorhersagewerts.",
      "missingValues": [
        "NA"
      ],
      "constraints": {
        "minimum": 0
      }
    },
    {
      "name": "loess_untere_schranke",
      "type": "number",
      "description": "Untere Grenze des punktweisen 95%-Konfidenzintervalls des LOESS-Vorhersagewerts.",
      "missingValues": [
        "NA"
      ],
      "constraints": {
        "minimum": 0
      }
    },
    {
      "name": "loess_aenderung",
      "type": "number",
      "description": "Änderung des LOESS-Vorhersagewerts zur Vorwoche, d.h. Quotient aus aktuellem Wert und dem Vorwochenwert.",
      "missingValues": [
        "NA"
      ]
    },
    {
      "name": "einwohner",
      "type": "integer",
      "description": "Einwohner, die an das Klärwerk des Standortes angeschlossen sind.",
      "missingValues": [
        "NA"
      ],
      "constraints": {
        "minimum": 0
      }
    },
    {
      "name": "laborwechsel",
      "type": "string",
      "description": "Laborwechsel bzw. Änderungen in den Labormethoden.",
      "missingValues": [
        "NA"
      ],
      "constraints": {
        "enum": [
          [
            "ja",
            "nein"
          ]
        ]
      }
    },
    {
      "name": "trend",
      "type": "string",
      "description": "Kategorisierte Veränderung des geglätteten LOESS-Wertes von einem Mittwoch zum Mittwoch der Vorwoche (siehe [Datenauswertung](https://github.com/robert-koch-institut/Abwassersurveillance_AMELAG/tree/main?tab=readme-ov-file#Datenauswertung))",
      "missingValues": [
        "NA"
      ],
      "constraints": {
        "enum": [
          [
            "Ansteigend",
            "Fallend",
            "Unverändert",
            "keine Daten vorhanden"
          ]
        ]
      }
    }
  ]
}